[
  {
    "id": "dot-hack-infection",
    "name": ".hack//Infection",
    "platformIds": ["playstation-2"],
    "tools": {
      "saveEditor": {
        "createdAt": "2026-04-12",
        "regions": ["🇪🇺", "🇺🇸", "🇯🇵"]
      }
    }
  },
  {
    "id": "dot-hack-mutation",
    "name": ".hack//Mutation",
    "platformIds": ["playstation-2"],
    "tools": {
      "saveEditor": {
        "createdAt": "2026-04-12",
        "regions": ["🇪🇺", "🇺🇸", "🇯🇵"]
      }
    }
  },
  {
    "id": "dot-hack-outbreak",
    "name": ".hack//Outbreak",
    "platformIds": ["playstation-2"],
    "tools": {
      "saveEditor": {
        "createdAt": "2026-04-12",
        "regions": ["🇪🇺", "🇺🇸", "🇯🇵"]
      }
    }
  },
  {
    "id": "dot-hack-quarantine",
    "name": ".hack//Quarantine",
    "platformIds": ["playstation-2"],
    "tools": {
      "saveEditor": {
        "createdAt": "2026-04-12",
        "regions": ["🇪🇺", "🇺🇸", "🇯🇵"]
      }
    }
  },
  {
    "id": "007-agent-under-fire",
    "name": "007: Agent Under Fire",
    "platformIds": ["playstation-2"],
    "tools": {
      "saveEditor": {
        "createdAt": "2025-06-07",
        "regions": ["🇪🇺", "🇺🇸", "🇰🇷"]
      }
    }
  },
  {
    "id": "1080-snowboarding",
    "name": "1080° Snowboarding",
    "platformIds": ["nintendo-64"],
    "tools": {
      "saveEditor": {
        "createdAt": "2023-12-16",
        "regions": ["🇪🇺", "🇺🇸", "🇯🇵"]
      }
    }
  },
  {
    "id": "3d-dot-game-heroes",
    "name": "3D Dot Game Heroes",
    "platformIds": ["playstation-3"],
    "tools": {
      "saveEditor": {
        "createdAt": "2025-07-07",
        "regions": ["🇪🇺", "🇺🇸", "🇯🇵"]
      }
    }
  },
  {
    "id": "actraiser",
    "name": "ActRaiser",
    "platformIds": ["super-nintendo"],
    "tools": {
      "saveEditor": {
        "createdAt": "2025-08-07",
        "regions": ["🇪🇺", "🇺🇸", "🇯🇵", "🇫🇷", "🇩🇪"]
      }
    }
  },
  {
    "id": "akumajou-dracula-x-chi-no-rondo",
    "name": "Akumajou Dracula X: Chi no Rondo",
    "platformIds": ["pc-engine-cd"],
    "tools": {
      "saveEditor": {
        "createdAt": "2023-12-16",
        "regions": ["🇯🇵"]
      }
    }
  },
  {
    "id": "azure-dreams",
    "name": "Azure Dreams",
    "platformIds": ["game-boy-color"],
    "tools": {
      "saveEditor": {
        "createdAt": "2026-04-08",
        "regions": ["🇪🇺", "🇺🇸", "🇯🇵"]
      }
    }
  },
  {
    "id": "banjo-kazooie",
    "name": "Banjo-Kazooie",
    "platformIds": ["nintendo-64"],
    "tools": {
      "saveEditor": {
        "createdAt": "2024-04-04",
        "regions": ["🇪🇺", "🇺🇸", "🇯🇵"]
      }
    }
  },
  {
    "id": "banjo-tooie",
    "name": "Banjo-Tooie",
    "platformIds": ["nintendo-64"],
    "tools": {
      "saveEditor": {
        "createdAt": "2025-04-16",
        "regions": ["🇪🇺", "🇺🇸", "🇯🇵", "🇦🇺"]
      }
    }
  },
  {
    "id": "bloodstained-ritual-of-the-night",
    "name": "Bloodstained: Ritual of the Night",
    "platformIds": ["steam"],
    "tools": {
      "saveEditor": {
        "createdAt": "2026-03-17",
        "regions": ["🏳️"]
      }
    }
  },
  {
    "id": "bomberman-64",
    "name": "Bomberman 64",
    "platformIds": ["nintendo-64"],
    "tools": {
      "saveEditor": {
        "createdAt": "2023-12-20",
        "regions": ["🇪🇺", "🇺🇸", "🇯🇵"]
      },
      "romEditor": {
        "createdAt": "2024-05-27",
        "regions": ["🇪🇺", "🇺🇸", "🇯🇵"]
      }
    }
  },
  {
    "id": "bouncer-the",
    "name": "Bouncer, The",
    "platformIds": ["playstation-2"],
    "tools": {
      "saveEditor": {
        "createdAt": "2025-03-31",
        "regions": ["🇪🇺", "🇺🇸", "🇯🇵"]
      }
    }
  },
  {
    "id": "castlevania",
    "name": "Castlevania",
    "platformIds": ["nintendo-64"],
    "tools": {
      "saveEditor": {
        "createdAt": "2025-08-16",
        "regions": ["🇪🇺", "🇺🇸", "🇯🇵"]
      }
    }
  },
  {
    "id": "castlevania-aria-of-sorrow",
    "name": "Castlevania: Aria of Sorrow",
    "platformIds": ["game-boy-advance"],
    "tools": {
      "saveEditor": {
        "createdAt": "2023-12-16",
        "regions": ["🇪🇺", "🇺🇸", "🇯🇵"]
      }
    }
  },
  {
    "id": "castlevania-circle-of-the-moon",
    "name": "Castlevania: Circle of the Moon",
    "platformIds": ["game-boy-advance"],
    "tools": {
      "saveEditor": {
        "createdAt": "2023-12-16",
        "regions": ["🇪🇺", "🇺🇸", "🇯🇵"]
      },
      "romEditor": {
        "createdAt": "2023-12-16",
        "regions": ["🇪🇺", "🇺🇸", "🇯🇵"]
      }
    }
  },
  {
    "id": "castlevania-dawn-of-sorrow",
    "name": "Castlevania: Dawn of Sorrow",
    "platformIds": ["nintendo-ds"],
    "tools": {
      "saveEditor": {
        "createdAt": "2024-03-24",
        "regions": ["🇪🇺", "🇺🇸", "🇯🇵"]
      }
    }
  },
  {
    "id": "castlevania-harmony-of-dissonance",
    "name": "Castlevania: Harmony of Dissonance",
    "platformIds": ["game-boy-advance"],
    "tools": {
      "saveEditor": {
        "createdAt": "2024-02-19",
        "regions": ["🇪🇺", "🇺🇸", "🇯🇵"]
      }
    }
  },
  {
    "id": "castlevania-order-of-ecclesia",
    "name": "Castlevania: Order of Ecclesia",
    "platformIds": ["nintendo-ds"],
    "tools": {
      "saveEditor": {
        "createdAt": "2024-11-21",
        "regions": ["🇪🇺", "🇺🇸", "🇯🇵", "🇰🇷"]
      }
    }
  },
  {
    "id": "castlevania-portrait-of-ruin",
    "name": "Castlevania: Portrait of Ruin",
    "platformIds": ["nintendo-ds"],
    "tools": {
      "saveEditor": {
        "createdAt": "2025-08-02",
        "regions": ["🇪🇺", "🇺🇸", "🇯🇵"]
      }
    }
  },
  {
    "id": "castlevania-symphony-of-the-night",
    "name": "Castlevania: Symphony of the Night",
    "platformIds": ["playstation"],
    "tools": {
      "saveEditor": {
        "createdAt": "2023-12-16",
        "regions": ["🇪🇺", "🇺🇸", "🇯🇵"]
      },
      "romEditor": {
        "createdAt": "2025-12-16",
        "regions": ["🇪🇺", "🇺🇸", "🇯🇵"]
      }
    }
  },
  {
    "id": "chrono-cross",
    "name": "Chrono Cross",
    "platformIds": ["playstation"],
    "tools": {
      "saveEditor": {
        "createdAt": "2025-11-24",
        "regions": ["🇺🇸", "🇯🇵"]
      }
    }
  },
  {
    "id": "chrono-trigger",
    "name": "Chrono Trigger",
    "platformIds": ["super-nintendo"],
    "tools": {
      "saveEditor": {
        "createdAt": "2025-09-04",
        "regions": ["🇺🇸", "🇯🇵"]
      },
      "romEditor": {
        "createdAt": "2026-01-15",
        "regions": ["🇺🇸", "🇯🇵"]
      }
    }
  },
  {
    "id": "crash-bandicoot",
    "name": "Crash Bandicoot",
    "platformIds": ["playstation"],
    "tools": {
      "saveEditor": {
        "createdAt": "2024-12-01",
        "regions": ["🇪🇺", "🇺🇸", "🇯🇵", "🇦🇺"]
      }
    }
  },
  {
    "id": "crisis-core-final-fantasy-vii-reunion",
    "name": "Crisis Core -Final Fantasy VII- Reunion",
    "platformIds": ["steam"],
    "tools": {
      "saveEditor": {
        "createdAt": "2025-11-29",
        "regions": ["🏳️"]
      }
    }
  },
  {
    "id": "ctr-crash-team-racing",
    "name": "CTR: Crash Team Racing",
    "platformIds": ["playstation"],
    "tools": {
      "saveEditor": {
        "createdAt": "2025-05-27",
        "regions": ["🇪🇺", "🇺🇸", "🇯🇵"]
      }
    }
  },
  {
    "id": "dead-or-alive-2",
    "name": "Dead or Alive 2",
    "platformIds": ["playstation-2"],
    "tools": {
      "saveEditor": {
        "createdAt": "2024-07-12",
        "regions": ["🇪🇺"]
      }
    }
  },
  {
    "id": "diablo-ii-lord-of-destruction",
    "name": "Diablo II: Lord of Destruction",
    "platformIds": ["windows"],
    "tools": {
      "saveEditor": {
        "createdAt": "2024-08-16",
        "regions": ["🏳️"]
      }
    }
  },
  {
    "id": "diddy-kong-racing",
    "name": "Diddy Kong Racing",
    "platformIds": ["nintendo-64"],
    "tools": {
      "saveEditor": {
        "createdAt": "2025-06-04",
        "regions": ["🇪🇺", "🇺🇸", "🇯🇵"]
      }
    }
  },
  {
    "id": "dissidia-012-duodecim-final-fantasy",
    "name": "Dissidia 012: Duodecim Final Fantasy",
    "platformIds": ["playstation-portable"],
    "tools": {
      "saveEditor": {
        "createdAt": "2024-12-12",
        "regions": ["🇪🇺", "🇺🇸", "🇯🇵"]
      }
    }
  },
  {
    "id": "donkey-kong-64",
    "name": "Donkey Kong 64",
    "platformIds": ["nintendo-64"],
    "tools": {
      "saveEditor": {
        "createdAt": "2025-11-04",
        "regions": ["🇪🇺", "🇺🇸", "🇯🇵"]
      }
    }
  },
  {
    "id": "donkey-kong-country",
    "name": "Donkey Kong Country",
    "platformIds": ["super-nintendo"],
    "tools": {
      "saveEditor": {
        "createdAt": "2025-08-27",
        "regions": ["🇪🇺", "🇺🇸", "🇯🇵"]
      }
    }
  },
  {
    "id": "donkey-kong-country-2-diddy-s-kong-quest",
    "name": "Donkey Kong Country 2: Diddy's Kong Quest",
    "platformIds": ["super-nintendo"],
    "tools": {
      "saveEditor": {
        "createdAt": "2026-01-03",
        "regions": ["🇪🇺", "🇺🇸", "🇯🇵", "🇩🇪"]
      }
    }
  },
  {
    "id": "donkey-kong-land",
    "name": "Donkey Kong Land",
    "platformIds": ["game-boy"],
    "tools": {
      "saveEditor": {
        "createdAt": "2023-12-16",
        "regions": ["🇪🇺", "🇺🇸", "🇯🇵"]
      }
    }
  },
  {
    "id": "dragon-ball-z-budokai-tenkaichi-2",
    "name": "Dragon Ball Z: Budokai Tenkaichi 2",
    "platformIds": ["playstation-2"],
    "tools": {
      "saveEditor": {
        "createdAt": "2025-09-14",
        "regions": ["🇪🇺", "🇺🇸", "🇯🇵", "🇰🇷"]
      }
    }
  },
  {
    "id": "dragon-quest-the-journey-of-the-cursed-king",
    "name": "Dragon Quest: The Journey of the Cursed King",
    "platformIds": ["playstation-2"],
    "tools": {
      "saveEditor": {
        "createdAt": "2025-08-20",
        "regions": ["🇪🇺", "🇺🇸", "🇯🇵"]
      }
    }
  },
  {
    "id": "f-zero",
    "name": "F-Zero",
    "platformIds": ["super-nintendo"],
    "tools": {
      "saveEditor": {
        "createdAt": "2025-12-22",
        "regions": ["🇪🇺", "🇺🇸", "🇯🇵"]
      }
    }
  },
  {
    "id": "f-zero-x",
    "name": "F-Zero X",
    "platformIds": ["nintendo-64"],
    "tools": {
      "saveEditor": {
        "createdAt": "2025-07-14",
        "regions": ["🇪🇺", "🇺🇸", "🇯🇵"]
      }
    }
  },
  {
    "id": "final-fantasy",
    "name": "Final Fantasy",
    "platformIds": ["nintendo-entertainment-system"],
    "tools": {
      "saveEditor": {
        "createdAt": "2025-06-28",
        "regions": ["🇺🇸", "🇯🇵"]
      }
    }
  },
  {
    "id": "final-fantasy-iv-pixel-remaster",
    "name": "Final Fantasy IV Pixel Remaster",
    "platformIds": ["steam"],
    "tools": {
      "saveEditor": {
        "createdAt": "2025-08-26",
        "regions": ["🏳️"]
      }
    }
  },
  {
    "id": "final-fantasy-vi",
    "name": "Final Fantasy VI",
    "platformIds": ["super-nintendo"],
    "tools": {
      "saveEditor": {
        "createdAt": "2026-04-16",
        "regions": ["🇺🇸", "🇯🇵"]
      }
    }
  },
  {
    "id": "final-fantasy-vii-remake",
    "name": "Final Fantasy VII Remake",
    "platformIds": ["steam"],
    "tools": {
      "saveEditor": {
        "createdAt": "2025-01-05",
        "regions": ["🏳️"]
      }
    }
  },
  {
    "id": "final-fantasy-vii-rebirth",
    "name": "Final Fantasy VII Rebirth",
    "platformIds": ["steam"],
    "tools": {
      "saveEditor": {
        "createdAt": "2025-05-01",
        "regions": ["🏳️"]
      }
    }
  },
  {
    "id": "final-fantasy-viii",
    "name": "Final Fantasy VIII",
    "platformIds": ["playstation"],
    "tools": {
      "saveEditor": {
        "createdAt": "2025-12-29",
        "regions": ["🇪🇺", "🇺🇸", "🇯🇵", "🇫🇷", "🇩🇪", "🇮🇹", "🇪🇸"]
      }
    }
  },
  {
    "id": "final-fantasy-ix",
    "name": "Final Fantasy IX",
    "platformIds": ["playstation"],
    "tools": {
      "saveEditor": {
        "createdAt": "2024-11-14",
        "regions": ["🇪🇺", "🇺🇸", "🇯🇵", "🇫🇷", "🇩🇪", "🇮🇹", "🇪🇸"]
      }
    }
  },
  {
    "id": "final-fantasy-tactics",
    "name": "Final Fantasy Tactics",
    "platformIds": ["playstation"],
    "tools": {
      "saveEditor": {
        "createdAt": "2025-08-12",
        "regions": ["🇺🇸", "🇯🇵"]
      }
    }
  },
  {
    "id": "final-fight-one",
    "name": "Final Fight One",
    "platformIds": ["game-boy-advance"],
    "tools": {
      "saveEditor": {
        "createdAt": "2024-04-04",
        "regions": ["🇪🇺", "🇺🇸", "🇯🇵"]
      }
    }
  },
  {
    "id": "fire-emblem-the-blazing-blade",
    "name": "Fire Emblem: The Blazing Blade",
    "platformIds": ["game-boy-advance"],
    "tools": {
      "saveEditor": {
        "createdAt": "2025-12-08",
        "regions": ["🇪🇺", "🇺🇸", "🇯🇵"]
      }
    }
  },
  {
    "id": "game-and-watch-gallery-3",
    "name": "Game & Watch Gallery 3",
    "platformIds": ["game-boy-color"],
    "tools": {
      "saveEditor": {
        "createdAt": "2023-12-16",
        "regions": ["🇪🇺", "🇺🇸", "🇯🇵", "🇦🇺"]
      }
    }
  },
  {
    "id": "game-boy-camera",
    "name": "Game Boy Camera",
    "platformIds": ["game-boy"],
    "tools": {
      "saveEditor": {
        "createdAt": "2024-08-17",
        "regions": ["🇪🇺", "🇺🇸", "🇯🇵"]
      }
    }
  },
  {
    "id": "gex-64-enter-the-gecko",
    "name": "Gex 64: Enter the Gecko",
    "platformIds": ["nintendo-64"],
    "tools": {
      "saveEditor": {
        "createdAt": "2026-02-20",
        "regions": ["🇪🇺", "🇺🇸"]
      }
    }
  },
  {
    "id": "golden-sun",
    "name": "Golden Sun",
    "platformIds": ["game-boy-advance"],
    "tools": {
      "saveEditor": {
        "createdAt": "2023-12-19",
        "regions": ["🇪🇺", "🇺🇸", "🇯🇵", "🇫🇷", "🇩🇪", "🇮🇹", "🇪🇸"]
      },
      "romEditor": {
        "createdAt": "2024-02-17",
        "regions": ["🇪🇺", "🇺🇸", "🇯🇵", "🇫🇷", "🇩🇪", "🇮🇹", "🇪🇸"]
      }
    }
  },
  {
    "id": "golden-sun-the-lost-age",
    "name": "Golden Sun: The Lost Age",
    "platformIds": ["game-boy-advance"],
    "tools": {
      "saveEditor": {
        "createdAt": "2024-11-26",
        "regions": ["🇪🇺", "🇺🇸", "🇯🇵", "🇫🇷", "🇩🇪", "🇮🇹", "🇪🇸"]
      }
    }
  },
  {
    "id": "goldeneye-007",
    "name": "GoldenEye 007",
    "platformIds": ["nintendo-64"],
    "tools": {
      "saveEditor": {
        "createdAt": "2023-12-16",
        "regions": ["🇪🇺", "🇺🇸", "🇯🇵"]
      }
    }
  },
  {
    "id": "grandia",
    "name": "Grandia",
    "platformIds": ["playstation"],
    "tools": {
      "saveEditor": {
        "createdAt": "2023-12-16",
        "regions": ["🇪🇺", "🇺🇸", "🇯🇵", "🇫🇷", "🇩🇪"]
      }
    }
  },
  {
    "id": "grandia-ii",
    "name": "Grandia II",
    "platformIds": ["playstation-2"],
    "tools": {
      "saveEditor": {
        "createdAt": "2024-08-04",
        "regions": ["🇪🇺", "🇺🇸", "🇯🇵"]
      }
    }
  },
  {
    "id": "half-minute-hero",
    "name": "Half-Minute Hero",
    "platformIds": ["playstation-portable"],
    "tools": {
      "saveEditor": {
        "createdAt": "2024-10-06",
        "regions": ["🇪🇺", "🇺🇸", "🇯🇵"]
      }
    }
  },
  {
    "id": "holy-magic-century",
    "name": "Holy Magic Century",
    "metaName": "Holy Magic Century (Quest 64)",
    "platformIds": ["nintendo-64"],
    "tools": {
      "saveEditor": {
        "createdAt": "2025-12-17",
        "regions": ["🇪🇺", "🇺🇸", "🇯🇵", "🇫🇷", "🇩🇪"]
      }
    }
  },
  {
    "id": "kingdom-hearts",
    "name": "Kingdom Hearts",
    "platformIds": ["playstation-2"],
    "tools": {
      "saveEditor": {
        "createdAt": "2024-03-04",
        "regions": ["🇪🇺", "🇺🇸", "🇯🇵", "🇫🇷", "🇩🇪", "🇮🇹", "🇪🇸", "🇦🇺"]
      }
    }
  },
  {
    "id": "kingdom-hearts-chain-of-memories",
    "name": "Kingdom Hearts: Chain of Memories",
    "platformIds": ["game-boy-advance"],
    "tools": {
      "saveEditor": {
        "createdAt": "2025-07-20",
        "regions": ["🇪🇺", "🇺🇸", "🇯🇵"]
      }
    }
  },
  {
    "id": "kirby-s-adventure",
    "name": "Kirby's Adventure",
    "platformIds": ["nintendo-entertainment-system"],
    "tools": {
      "saveEditor": {
        "createdAt": "2024-11-22",
        "regions": ["🇪🇺", "🇺🇸", "🇯🇵", "🇫🇷", "🇩🇪", "🇨🇦"]
      }
    }
  },
  {
    "id": "konami-krazy-racers",
    "name": "Konami Krazy Racers",
    "platformIds": ["game-boy-advance"],
    "tools": {
      "saveEditor": {
        "createdAt": "2023-12-16",
        "regions": ["🇪🇺", "🇺🇸", "🇯🇵"]
      }
    }
  },
  {
    "id": "kurukuru-kururin",
    "name": "Kurukuru Kururin",
    "platformIds": ["game-boy-advance"],
    "tools": {
      "saveEditor": {
        "createdAt": "2026-01-05",
        "regions": ["🇪🇺", "🇯🇵"]
      }
    }
  },
  {
    "id": "legend-of-zelda-the-a-link-to-the-past",
    "name": "Legend of Zelda, The: A Link to the Past",
    "platformIds": ["super-nintendo"],
    "tools": {
      "saveEditor": {
        "createdAt": "2024-01-06",
        "regions": ["🇪🇺", "🇺🇸", "🇯🇵", "🇫🇷", "🇩🇪", "🇨🇦"]
      }
    }
  },
  {
    "id": "legend-of-zelda-the-link-s-awakening-dx",
    "name": "Legend of Zelda, The: Link's Awakening DX",
    "platformIds": ["game-boy-color"],
    "tools": {
      "saveEditor": {
        "createdAt": "2023-12-16",
        "regions": ["🇪🇺", "🇺🇸", "🇯🇵", "🇫🇷", "🇩🇪"]
      }
    }
  },
  {
    "id": "legend-of-zelda-the-majora-s-mask",
    "name": "Legend of Zelda, The: Majora's Mask",
    "platformIds": ["nintendo-64"],
    "tools": {
      "saveEditor": {
        "createdAt": "2023-12-29",
        "regions": ["🇪🇺", "🇺🇸", "🇯🇵"]
      }
    }
  },
  {
    "id": "legend-of-zelda-the-ocarina-of-time",
    "name": "Legend of Zelda, The: Ocarina of Time",
    "platformIds": ["nintendo-64"],
    "tools": {
      "saveEditor": {
        "createdAt": "2025-06-20",
        "regions": ["🇪🇺", "🇺🇸", "🇯🇵"]
      }
    }
  },
  {
    "id": "legend-of-zelda-the-oracle-of-ages",
    "name": "Legend of Zelda, The: Oracle of Ages",
    "platformIds": ["game-boy-color"],
    "tools": {
      "saveEditor": {
        "createdAt": "2025-05-13",
        "regions": ["🇪🇺", "🇺🇸", "🇯🇵", "🇦🇺"]
      }
    }
  },
  {
    "id": "legend-of-zelda-the-oracle-of-seasons",
    "name": "Legend of Zelda, The: Oracle of Seasons",
    "platformIds": ["game-boy-color"],
    "tools": {
      "saveEditor": {
        "createdAt": "2025-05-13",
        "regions": ["🇪🇺", "🇺🇸", "🇯🇵", "🇦🇺"]
      }
    }
  },
  {
    "id": "legend-of-zelda-the-the-minish-cap",
    "name": "Legend of Zelda, The: The Minish Cap",
    "platformIds": ["game-boy-advance"],
    "tools": {
      "saveEditor": {
        "createdAt": "2025-09-22",
        "regions": ["🇪🇺", "🇺🇸", "🇯🇵"]
      }
    }
  },
  {
    "id": "luigi-s-mansion",
    "name": "Luigi's Mansion",
    "platformIds": ["gamecube"],
    "tools": {
      "saveEditor": {
        "createdAt": "2025-06-16",
        "regions": ["🇪🇺", "🇺🇸", "🇯🇵"]
      }
    }
  },
  {
    "id": "lylat-wars",
    "name": "Lylat Wars",
    "metaName": "Lylat Wars (Star Fox 64)",
    "platformIds": ["nintendo-64"],
    "tools": {
      "saveEditor": {
        "createdAt": "2024-11-24",
        "regions": ["🇪🇺", "🇺🇸", "🇯🇵", "🇦🇺"]
      }
    }
  },
  {
    "id": "mario-kart-64",
    "name": "Mario Kart 64",
    "platformIds": ["nintendo-64"],
    "tools": {
      "saveEditor": {
        "createdAt": "2025-07-15",
        "regions": ["🇪🇺", "🇺🇸", "🇯🇵"]
      }
    }
  },
  {
    "id": "mario-party",
    "name": "Mario Party",
    "platformIds": ["nintendo-64"],
    "tools": {
      "saveEditor": {
        "createdAt": "2024-10-07",
        "regions": ["🇪🇺", "🇺🇸", "🇯🇵"]
      }
    }
  },
  {
    "id": "mario-party-2",
    "name": "Mario Party 2",
    "platformIds": ["nintendo-64"],
    "tools": {
      "saveEditor": {
        "createdAt": "2026-03-18",
        "regions": ["🇪🇺", "🇺🇸", "🇯🇵"]
      }
    }
  },
  {
    "id": "marvel-vs-capcom-2-new-age-of-heroes",
    "name": "Marvel vs. Capcom 2: New Age of Heroes",
    "platformIds": ["dreamcast"],
    "tools": {
      "saveEditor": {
        "createdAt": "2024-01-10",
        "regions": ["🇪🇺", "🇺🇸", "🇯🇵"]
      }
    }
  },
  {
    "id": "mission-impossible",
    "name": "Mission: Impossible",
    "platformIds": ["nintendo-64"],
    "tools": {
      "saveEditor": {
        "createdAt": "2025-06-27",
        "regions": ["🇪🇺", "🇺🇸", "🇫🇷", "🇩🇪", "🇮🇹", "🇪🇸"]
      }
    }
  },
  {
    "id": "muramasa-the-demon-blade",
    "name": "Muramasa: The Demon Blade",
    "platformIds": ["wii"],
    "tools": {
      "saveEditor": {
        "createdAt": "2025-06-26",
        "regions": ["🇪🇺", "🇺🇸", "🇯🇵"]
      }
    }
  },
  {
    "id": "mystic-quest-legend",
    "name": "Mystic Quest Legend",
    "metaName": "Mystic Quest Legend (Final Fantasy Mystic Quest)",
    "platformIds": ["super-nintendo"],
    "tools": {
      "saveEditor": {
        "createdAt": "2023-12-16",
        "regions": ["🇪🇺", "🇺🇸", "🇯🇵", "🇫🇷", "🇩🇪"]
      },
      "romEditor": {
        "createdAt": "2023-12-16",
        "regions": ["🇪🇺", "🇺🇸", "🇯🇵", "🇫🇷", "🇩🇪"]
      }
    }
  },
  {
    "id": "mystical-ninja-starring-goemon",
    "name": "Mystical Ninja Starring Goemon",
    "platformIds": ["nintendo-64"],
    "tools": {
      "saveEditor": {
        "createdAt": "2024-12-19",
        "regions": ["🇪🇺", "🇺🇸", "🇯🇵"]
      }
    }
  },
  {
    "id": "mystical-ninja-2-starring-goemon",
    "name": "Mystical Ninja 2 Starring Goemon",
    "metaName": "Mystical Ninja 2 Starring Goemon (Goemon's Great Adventure)",
    "platformIds": ["nintendo-64"],
    "tools": {
      "saveEditor": {
        "createdAt": "2024-01-28",
        "regions": ["🇪🇺", "🇺🇸", "🇯🇵"]
      }
    }
  },
  {
    "id": "octopath-traveler",
    "name": "Octopath Traveler",
    "platformIds": ["switch", "steam"],
    "tools": {
      "saveEditor": {
        "createdAt": "2025-11-15",
        "regions": ["🏳️"]
      }
    }
  },
  {
    "id": "octopath-traveler-ii",
    "name": "Octopath Traveler II",
    "platformIds": ["switch", "steam"],
    "tools": {
      "saveEditor": {
        "createdAt": "2025-11-15",
        "regions": ["🏳️"]
      }
    }
  },
  {
    "id": "paper-mario",
    "name": "Paper Mario",
    "platformIds": ["nintendo-64"],
    "tools": {
      "saveEditor": {
        "createdAt": "2026-04-04",
        "regions": ["🇪🇺", "🇺🇸", "🇯🇵"]
      }
    }
  },
  {
    "id": "paper-mario-the-thousand-year-door",
    "name": "Paper Mario: The Thousand-Year Door",
    "platformIds": ["gamecube"],
    "tools": {
      "saveEditor": {
        "createdAt": "2025-09-10",
        "regions": ["🇪🇺", "🇺🇸", "🇯🇵"]
      }
    }
  },
  {
    "id": "pokemon-red-blue-and-yellow",
    "name": "Pokémon Red, Blue and Yellow",
    "platformIds": ["game-boy"],
    "tools": {
      "saveEditor": {
        "createdAt": "2025-07-27",
        "regions": ["🇪🇺", "🇺🇸", "🇯🇵", "🇫🇷", "🇩🇪", "🇮🇹", "🇪🇸"]
      }
    }
  },
  {
    "id": "pokemon-gold-silver-and-crystal",
    "name": "Pokémon Gold, Silver and Crystal",
    "platformIds": ["game-boy-color"],
    "tools": {
      "saveEditor": {
        "createdAt": "2026-03-13",
        "regions": ["🇪🇺", "🇺🇸", "🇯🇵", "🇫🇷", "🇩🇪", "🇮🇹", "🇪🇸", "🇦🇺"]
      }
    }
  },
  {
    "id": "pokemon-snap",
    "name": "Pokémon Snap",
    "platformIds": ["nintendo-64"],
    "tools": {
      "saveEditor": {
        "createdAt": "2026-03-05",
        "regions": ["🇪🇺", "🇺🇸", "🇯🇵", "🇫🇷", "🇩🇪", "🇮🇹", "🇪🇸", "🇦🇺"]
      }
    }
  },
  {
    "id": "pokemon-trading-card-game",
    "name": "Pokémon Trading Card Game",
    "platformIds": ["game-boy-color"],
    "tools": {
      "saveEditor": {
        "createdAt": "2024-07-25",
        "regions": ["🇪🇺", "🇺🇸", "🇯🇵", "🇦🇺"]
      }
    }
  },
  {
    "id": "rayman",
    "name": "Rayman",
    "platformIds": ["playstation"],
    "tools": {
      "saveEditor": {
        "createdAt": "2023-12-23",
        "regions": ["🇪🇺", "🇺🇸", "🇯🇵"]
      }
    }
  },
  {
    "id": "rayman-2-the-great-escape",
    "name": "Rayman 2: The Great Escape",
    "platformIds": ["nintendo-64"],
    "tools": {
      "saveEditor": {
        "createdAt": "2026-02-10",
        "regions": ["🇪🇺", "🇺🇸"]
      }
    }
  },
  {
    "id": "resident-evil",
    "name": "Resident Evil",
    "platformIds": ["playstation"],
    "tools": {
      "saveEditor": {
        "createdAt": "2024-03-17",
        "regions": ["🇪🇺", "🇺🇸", "🇯🇵", "🇫🇷", "🇩🇪"]
      }
    }
  },
  {
    "id": "rogue-legacy",
    "name": "Rogue Legacy",
    "platformIds": ["steam"],
    "tools": {
      "saveEditor": {
        "createdAt": "2024-08-31",
        "regions": ["🏳️"]
      }
    }
  },
  {
    "id": "shining-force-3",
    "name": "Shining Force 3",
    "platformIds": ["saturn"],
    "tools": {
      "saveEditor": {
        "createdAt": "2023-12-16",
        "regions": ["🇪🇺", "🇺🇸", "🇯🇵"]
      },
      "romEditor": {
        "createdAt": "2024-07-08",
        "regions": ["🇪🇺", "🇺🇸", "🇯🇵"]
      }
    }
  },
  {
    "id": "shining-the-holy-ark",
    "name": "Shining the Holy Ark",
    "platformIds": ["saturn"],
    "tools": {
      "saveEditor": {
        "createdAt": "2026-02-17",
        "regions": ["🇪🇺", "🇺🇸", "🇯🇵"]
      },
      "romEditor": {
        "createdAt": "2026-02-24",
        "regions": ["🇪🇺", "🇺🇸", "🇯🇵"]
      }
    }
  },
  {
    "id": "skies-of-arcadia-legends",
    "name": "Skies of Arcadia Legends",
    "platformIds": ["gamecube"],
    "tools": {
      "saveEditor": {
        "createdAt": "2024-12-25",
        "regions": ["🇪🇺", "🇺🇸", "🇯🇵"]
      },
      "romEditor": {
        "createdAt": "2025-02-17",
        "regions": ["🇪🇺", "🇺🇸", "🇯🇵"]
      },
      "randomizer": {
        "createdAt": "2025-02-17",
        "regions": ["🇪🇺", "🇺🇸", "🇯🇵"]
      }
    }
  },
  {
    "id": "solatorobo-red-the-hunter",
    "name": "Solatorobo: Red the Hunter",
    "platformIds": ["nintendo-ds"],
    "tools": {
      "saveEditor": {
        "createdAt": "2026-01-25",
        "regions": ["🇪🇺", "🇺🇸", "🇯🇵"]
      }
    }
  },
  {
    "id": "soleil",
    "name": "Soleil",
    "metaName": "Soleil (Crusader of Centy)",
    "platformIds": ["mega-drive"],
    "tools": {
      "saveEditor": {
        "createdAt": "2024-04-29",
        "regions": ["🇪🇺", "🇺🇸", "🇯🇵", "🇫🇷", "🇩🇪", "🇪🇸", "🇰🇷"]
      },
      "romEditor": {
        "createdAt": "2024-04-29",
        "regions": ["🇪🇺", "🇺🇸", "🇯🇵", "🇫🇷", "🇩🇪", "🇪🇸", "🇰🇷"]
      }
    }
  },
  {
    "id": "sonic-3",
    "name": "Sonic 3",
    "platformIds": ["mega-drive"],
    "tools": {
      "saveEditor": {
        "createdAt": "2023-12-16",
        "regions": ["🇪🇺", "🇺🇸", "🇯🇵"]
      }
    }
  },
  {
    "id": "sonic-advance",
    "name": "Sonic Advance",
    "platformIds": ["game-boy-advance"],
    "tools": {
      "saveEditor": {
        "createdAt": "2026-01-31",
        "regions": ["🇪🇺", "🇺🇸", "🇯🇵"]
      }
    }
  },
  {
    "id": "sonic-advance-2",
    "name": "Sonic Advance 2",
    "platformIds": ["game-boy-advance"],
    "tools": {
      "saveEditor": {
        "createdAt": "2026-01-31",
        "regions": ["🇪🇺", "🇺🇸", "🇯🇵"]
      }
    }
  },
  {
    "id": "sonic-advance-3",
    "name": "Sonic Advance 3",
    "platformIds": ["game-boy-advance"],
    "tools": {
      "saveEditor": {
        "createdAt": "2026-01-31",
        "regions": ["🇪🇺", "🇺🇸", "🇯🇵"]
      }
    }
  },
  {
    "id": "sonic-adventure-2-battle",
    "name": "Sonic Adventure 2: Battle",
    "platformIds": ["gamecube"],
    "tools": {
      "saveEditor": {
        "createdAt": "2024-09-27",
        "regions": ["🇪🇺", "🇺🇸", "🇯🇵"]
      }
    }
  },
  {
    "id": "sonic-rush",
    "name": "Sonic Rush",
    "platformIds": ["nintendo-ds"],
    "tools": {
      "saveEditor": {
        "createdAt": "2026-01-31",
        "regions": ["🇪🇺", "🇺🇸", "🇯🇵"]
      }
    }
  },
  {
    "id": "super-mario-64",
    "name": "Super Mario 64",
    "platformIds": ["nintendo-64"],
    "tools": {
      "saveEditor": {
        "createdAt": "2025-04-03",
        "regions": ["🇪🇺", "🇺🇸", "🇯🇵"]
      }
    }
  },
  {
    "id": "super-mario-galaxy",
    "name": "Super Mario Galaxy",
    "platformIds": ["wii"],
    "tools": {
      "saveEditor": {
        "createdAt": "2025-09-16",
        "regions": ["🇪🇺", "🇺🇸", "🇯🇵", "🇦🇺", "🇰🇷"]
      }
    }
  },
  {
    "id": "super-mario-galaxy-2",
    "name": "Super Mario Galaxy 2",
    "platformIds": ["wii"],
    "tools": {
      "saveEditor": {
        "createdAt": "2025-12-13",
        "regions": ["🇪🇺", "🇺🇸", "🇯🇵", "🇰🇷"]
      }
    }
  },
  {
    "id": "super-mario-kart",
    "name": "Super Mario Kart",
    "platformIds": ["super-nintendo"],
    "tools": {
      "saveEditor": {
        "createdAt": "2025-07-04",
        "regions": ["🇪🇺", "🇺🇸", "🇯🇵"]
      }
    }
  },
  {
    "id": "super-mario-sunshine",
    "name": "Super Mario Sunshine",
    "platformIds": ["gamecube"],
    "tools": {
      "saveEditor": {
        "createdAt": "2025-08-05",
        "regions": ["🇪🇺", "🇺🇸", "🇯🇵", "🇨🇦", "🇰🇷"]
      }
    }
  },
  {
    "id": "super-metroid",
    "name": "Super Metroid",
    "platformIds": ["super-nintendo"],
    "tools": {
      "saveEditor": {
        "createdAt": "2025-10-25",
        "regions": ["🇪🇺", "🇺🇸", "🇯🇵"]
      }
    }
  },
  {
    "id": "super-punch-out",
    "name": "Super Punch Out!!",
    "platformIds": ["super-nintendo"],
    "tools": {
      "saveEditor": {
        "createdAt": "2025-07-03",
        "regions": ["🇪🇺", "🇺🇸", "🇯🇵"]
      }
    }
  },
  {
    "id": "super-smash-bros",
    "name": "Super Smash Bros.",
    "platformIds": ["nintendo-64"],
    "tools": {
      "saveEditor": {
        "createdAt": "2023-12-16",
        "regions": ["🇪🇺", "🇺🇸", "🇯🇵", "🇦🇺"]
      }
    }
  },
  {
    "id": "super-smash-bros-melee",
    "name": "Super Smash Bros. Melee",
    "platformIds": ["gamecube"],
    "tools": {
      "saveEditor": {
        "createdAt": "2024-10-28",
        "regions": ["🇪🇺", "🇺🇸", "🇯🇵"]
      }
    }
  },
  {
    "id": "super-street-fighter-ii-turbo-revival",
    "name": "Super Street Fighter II Turbo Revival",
    "platformIds": ["game-boy-advance"],
    "tools": {
      "saveEditor": {
        "createdAt": "2023-12-16",
        "regions": ["🇪🇺", "🇺🇸", "🇯🇵"]
      }
    }
  },
  {
    "id": "theatrhythm-final-fantasy-curtain-call",
    "name": "Theatrhythm Final Fantasy: Curtain Call",
    "platformIds": ["nintendo-3ds"],
    "tools": {
      "saveEditor": {
        "createdAt": "2025-06-23",
        "regions": ["🇪🇺", "🇺🇸", "🇯🇵"]
      }
    }
  },
  {
    "id": "timesplitters-2",
    "name": "TimeSplitters 2",
    "platformIds": ["playstation-2"],
    "tools": {
      "saveEditor": {
        "createdAt": "2024-10-15",
        "regions": ["🇪🇺", "🇺🇸", "🇯🇵"]
      }
    }
  },
  {
    "id": "tomb-raider-ii-starring-lara-croft",
    "name": "Tomb Raider II: Starring Lara Croft",
    "platformIds": ["playstation"],
    "tools": {
      "saveEditor": {
        "createdAt": "2025-11-08",
        "regions": ["🇪🇺", "🇺🇸", "🇯🇵", "🇫🇷", "🇩🇪", "🇮🇹"]
      }
    }
  },
  {
    "id": "tony-hawk-s-skateboarding",
    "name": "Tony Hawk's Skateboarding",
    "metaName": "Tony Hawk's Skateboarding (Tony Hawk's Pro Skater)",
    "platformIds": ["playstation"],
    "tools": {
      "saveEditor": {
        "createdAt": "2026-02-09",
        "regions": ["🇪🇺", "🇺🇸", "🇯🇵"]
      }
    }
  },
  {
    "id": "wario-land-super-mario-land-3",
    "name": "Wario Land: Super Mario Land 3",
    "platformIds": ["game-boy"],
    "tools": {
      "saveEditor": {
        "createdAt": "2023-12-16",
        "regions": ["🏳️"]
      }
    }
  },
  {
    "id": "wario-land-3",
    "name": "Wario Land 3",
    "platformIds": ["game-boy-color"],
    "tools": {
      "saveEditor": {
        "createdAt": "2024-11-01",
        "regions": ["🏳️"]
      }
    }
  },
  {
    "id": "wario-land-4",
    "name": "Wario Land 4",
    "platformIds": ["game-boy-advance"],
    "tools": {
      "saveEditor": {
        "createdAt": "2026-04-08",
        "regions": ["🇪🇺", "🇺🇸", "🇯🇵"]
      }
    }
  }
]
